{
  "627e71b0bf99d487c43fb494522e7af8": "[FP&A Analysis: AAPL | Period: 2009 to 2022]\nRevenue: $394,328M | CAGR: 18.61% | YoY latest: 7.79% | Trend: decelerating\nYoY last 5: 2018:+15.9%, 2019:-2.0%, 2020:+5.5%, 2021:+33.3%, 2022:+7.8%\nEBITDA margin: 33.1% | 5yr avg: 32.0% | Trend: accelerating\nOperating CF: $122,151M | Avg CF: $63,995M | Cash conv ratio: 1.224\nDebt/Equity: 2.37 | Current ratio: 0.88 | ROE: 197.0% | ROA: 28.3%\nOperating leverage: Strong operating leverage: margins expanding faster than revenue growth\nBase revenue: $394,328M\nScenarios:\n  Best Case: growth=42.9% Y1=$563,653M Y3=$1,151,648M prob=0.25\n  Base Case: growth=20.4% Y1=$474,872M Y3=$688,677M prob=0.5\n  Worst Case: growth=-2.1% Y1=$386,092M Y3=$370,133M prob=0.25\nRisk level: CRITICAL | Flags: Debt/Equity ratio (2.37) exceeds threshold (1.5); Current ratio (0.88) below 1.0 \u2014 liquidity risk\nSector: IT",
  "0c2aaa91d5adc05311f5f678c3b983f7": "[FP&A Analysis: AMZN | Period: 2009 to 2022]\nRevenue: $513,983M | CAGR: 26.38% | YoY latest: 9.40% | Trend: decelerating\nYoY last 5: 2018:+30.9%, 2019:+20.5%, 2020:+37.6%, 2021:+21.7%, 2022:+9.4%\nEBITDA margin: 10.5% | 5yr avg: 8.4% | Trend: declining\nOperating CF: $46,752M | Avg CF: $21,655M | Cash conv ratio: -17.176\nDebt/Equity: 0.46 | Current ratio: 0.94 | ROE: -1.9% | ROA: -0.6%\nOperating leverage: Moderate operating leverage: margins improving alongside revenue\nBase revenue: $513,983M\nScenarios:\n  Best Case: growth=35.8% Y1=$697,825M Y3=$1,286,298M prob=0.25\n  Base Case: growth=26.7% Y1=$651,104M Y3=$1,044,847M prob=0.5\n  Worst Case: growth=17.6% Y1=$604,382M Y3=$835,675M prob=0.25\nRisk level: CRITICAL | Flags: Current ratio (0.94) below 1.0 \u2014 liquidity risk\nSector: LOGI",
  "3281e4270a030001002ff88fa69540e4": "[FP&A Analysis: GOOG | Period: 2009 to 2022]\nRevenue: $282,836M | CAGR: 21.03% | YoY latest: 9.78% | Trend: stable\nYoY last 5: 2018:+23.4%, 2019:+18.3%, 2020:+12.8%, 2021:+41.2%, 2022:+9.8%\nEBITDA margin: 32.1% | 5yr avg: 33.5% | Trend: accelerating\nOperating CF: $91,495M | Avg CF: $38,838M | Cash conv ratio: 1.526\nDebt/Equity: 0.06 | Current ratio: 2.38 | ROE: 23.4% | ROA: 16.4%\nOperating leverage: Limited operating leverage: margins not expanding with revenue growth\nBase revenue: $282,836M\nScenarios:\n  Best Case: growth=29.2% Y1=$365,365M Y3=$609,693M prob=0.25\n  Base Case: growth=21.3% Y1=$342,972M Y3=$504,319M prob=0.5\n  Worst Case: growth=13.3% Y1=$320,579M Y3=$411,846M prob=0.25\nRisk level: LOW | Flags: None\nSector: IT",
  "e71ef57148bad1d53665e80d6507e724": "[FP&A Analysis: SHLDQ | Period: 2009 to 2018]\nRevenue: $16,702M | CAGR: -10.81% | YoY latest: -24.56% | Trend: declining\nYoY last 5: 2014:-9.2%, 2015:-13.8%, 2016:-19.4%, 2017:-12.0%, 2018:-24.6%\nEBITDA margin: -0.3% | 5yr avg: -0.5% | Trend: decelerating\nOperating CF: $-1,842M | Avg CF: $-584M | Cash conv ratio: 4.809\nDebt/Equity: -1.11 | Current ratio: 0.78 | ROE: 10.3% | ROA: -5.3%\nOperating leverage: Strong operating leverage: margins expanding faster than revenue growth\nBase revenue: $16,702M\nScenarios:\n  Best Case: growth=-2.7% Y1=$16,248M Y3=$15,377M prob=0.25\n  Base Case: growth=-10.5% Y1=$14,948M Y3=$11,974M prob=0.5\n  Worst Case: growth=-18.3% Y1=$13,649M Y3=$9,115M prob=0.25\nRisk level: CRITICAL | Flags: Current ratio (0.78) below 1.0 \u2014 liquidity risk\nSector: Finance",
  "1ae12bbc972a415c7658dd37903b36f1": "[FP&A Analysis: MCD | Period: 2009 to 2022]\nRevenue: $23,183M | CAGR: 0.15% | YoY latest: -0.17% | Trend: accelerating\nYoY last 5: 2018:-6.8%, 2019:+0.5%, 2020:-10.1%, 2021:+20.9%, 2022:-0.2%\nEBITDA margin: 48.5% | 5yr avg: 41.7% | Trend: decelerating\nOperating CF: $7,387M | Avg CF: $6,864M | Cash conv ratio: 1.196\nDebt/Equity: -5.98 | Current ratio: 1.43 | ROE: -102.9% | ROA: 12.2%\nOperating leverage: Strong operating leverage: margins expanding faster than revenue growth\nBase revenue: $23,183M\nScenarios:\n  Best Case: growth=9.1% Y1=$25,297M Y3=$30,122M prob=0.25\n  Base Case: growth=0.5% Y1=$23,292M Y3=$23,514M prob=0.5\n  Worst Case: growth=-8.2% Y1=$21,288M Y3=$17,951M prob=0.25\nRisk level: MODERATE | Flags: None\nSector: FOOD"
}